infermedica_api/__init__.py
infermedica_api/exceptions.py
infermedica_api/webservice.py
infermedica_api/models/__init__.py
infermedica_api/models/base.py
infermedica_api/models/condition.py
infermedica_api/models/diagnosis.py
infermedica_api/models/explain.py
infermedica_api/models/lab_test.py
infermedica_api/models/observation.py
infermedica_api/models/parse.py
infermedica_api/models/risk_factor.py
infermedica_api/models/symptom.py
infermedica_api-0.1.0.dist-info/DESCRIPTION.rst
infermedica_api-0.1.0.dist-info/METADATA
infermedica_api-0.1.0.dist-info/RECORD
infermedica_api-0.1.0.dist-info/WHEEL
infermedica_api-0.1.0.dist-info/metadata.json
infermedica_api-0.1.0.dist-info/top_level.txt
