Metadata-Version: 2.0
Name: infermedica-api
Version: 0.1.0
Summary: The Infermedica Python client for Infermedica API.
Home-page: https://github.com/infermedica/python-api
Author: Infermedica
Author-email: office@infermedica.com
License: Apache 2.0
Keywords: infermedica medical api library rest http
Platform: UNKNOWN
Classifier: Environment :: Web Environment
Classifier: Intended Audience :: Developers
Classifier: Intended Audience :: Healthcare Industry
Classifier: License :: OSI Approved :: Apache Software License
Classifier: Natural Language :: English
Classifier: Operating System :: OS Independent
Classifier: Programming Language :: Python
Classifier: Programming Language :: Python :: 2
Classifier: Programming Language :: Python :: 2.7
Classifier: Programming Language :: Python :: 3
Classifier: Programming Language :: Python :: 3.4
Classifier: Programming Language :: Python :: 3.5
Classifier: Topic :: Software Development :: Libraries
Classifier: Topic :: Scientific/Engineering :: Medical Science Apps.
Classifier: Topic :: Scientific/Engineering :: Artificial Intelligence
Requires-Dist: requests (>=1.0.0)
